diatomics/__init__.py
diatomics/__main__.py
diatomics/connector.py
diatomics/diatomic.py
diatomics/data/__init__.py
diatomics/data/moleculedata.csv
diatomics-0.2.0.dist-info/METADATA
diatomics-0.2.0.dist-info/WHEEL
diatomics-0.2.0.dist-info/RECORD
